{
    "fluentMethods": true,
    "relationships": [],
    "fields": [
        {
            "fieldName": "username",
            "fieldType": "String"
        },
        {
            "fieldName": "description",
            "fieldType": "byte[]",
            "fieldTypeBlobContent": "text"
        },
        {
            "fieldName": "name",
            "fieldType": "String"
        },
        {
            "fieldName": "responsible",
            "fieldType": "String"
        },
        {
            "fieldName": "startTime",
            "fieldType": "String"
        },
        {
            "fieldName": "endTime",
            "fieldType": "String"
        },
        {
            "fieldName": "extra",
            "fieldType": "String"
        },
        {
            "fieldName": "isActive",
            "fieldType": "Boolean"
        },
        {
            "fieldName": "createTime",
            "fieldType": "ZonedDateTime"
        },
        {
            "fieldName": "updateTime",
            "fieldType": "ZonedDateTime"
        }
    ],
    "changelogDate": "20180507150113",
    "entityTableName": "b_work_project",
    "dto": "no",
    "pagination": "no",
    "service": "serviceImpl"
}